consolebundle/CommandManager.py
consolebundle/CommandRunner.py
consolebundle/ConsoleArgumentParser.py
consolebundle/ConsoleBundle.py
consolebundle/ConsoleBundleTest.py
consolebundle/ConsoleCommand.py
consolebundle/ConsoleLoggerFactory.py
consolebundle/StrToBool.py
consolebundle/_config/config.yaml
consolebundle/_config/config_test.yaml
consolebundle/detector.py
console_bundle-0.5.1.dist-info/entry_points.txt
console_bundle-0.5.1.dist-info/WHEEL
console_bundle-0.5.1.dist-info/METADATA
console_bundle-0.5.1.dist-info/RECORD
