Metadata-Version: 2.1
Name: console-bundle
Version: 0.5.1
Summary: Console Bundle for the Pyfony Framework
Home-page: https://github.com/pyfony/console-bundle
License: MIT
Author: Jiri Koutny
Author-email: jiri.koutny@datasentics.com
Requires-Python: >=3.7,<4.0
Classifier: License :: OSI Approved :: MIT License
Classifier: Operating System :: OS Independent
Classifier: Programming Language :: Python :: 3
Classifier: Programming Language :: Python :: 3.7
Classifier: Programming Language :: Python :: 3.8
Classifier: Programming Language :: Python :: 3.9
Requires-Dist: colorlog (>=4.0,<5.0)
Requires-Dist: pyfony-bundles (>=0.4.0,<0.5.0)
Requires-Dist: pyfony-core (>=0.8.0,<0.9.0)
Requires-Dist: python-dotenv (>=0.13.0,<1.0.0)
Project-URL: Repository, https://github.com/pyfony/console-bundle
